msc_pyparser.py
msc_pyparser-1.2.2.data/data/parser.out
msc_pyparser-1.2.2.data/data/parsetab.py
msc_pyparser-1.2.2.dist-info/AUTHORS
msc_pyparser-1.2.2.dist-info/COPYING
msc_pyparser-1.2.2.dist-info/LICENSE
msc_pyparser-1.2.2.dist-info/METADATA
msc_pyparser-1.2.2.dist-info/WHEEL
msc_pyparser-1.2.2.dist-info/top_level.txt
msc_pyparser-1.2.2.dist-info/RECORD
