Metadata-Version: 2.2
Name: msc_pyparser
Version: 1.2.2
Summary: A ModSecurity config parser for Python 3
Home-page: https://github.com/digitalwave/msc_pyparser
Author: Ervin Hegedus
Author-email: airween@digitalwave.hu
Maintainer: Ervin Hegedus
Maintainer-email: airween@digitalwave.hu
License: GPLv3
Classifier: Topic :: Text Processing
Requires-Python: >=3
License-File: LICENSE
License-File: COPYING
License-File: AUTHORS
Requires-Dist: ply>=3.0
Dynamic: author
Dynamic: author-email
Dynamic: classifier
Dynamic: description
Dynamic: home-page
Dynamic: license
Dynamic: maintainer
Dynamic: maintainer-email
Dynamic: requires-dist
Dynamic: requires-python
Dynamic: summary
